myfirsteverpackagesfrompackageanditisunique/myfirstmodule.py
myfirsteverpackagesfrompackageanditisunique/setup.py
myfirstpackage/myfirstmodule.py
myfirstpackage/setup.py
myfirsteverpackagesfrompackageanditisunique-0.1.dist-info/METADATA
myfirsteverpackagesfrompackageanditisunique-0.1.dist-info/WHEEL
myfirsteverpackagesfrompackageanditisunique-0.1.dist-info/top_level.txt
myfirsteverpackagesfrompackageanditisunique-0.1.dist-info/RECORD
