Metadata-Version: 2.1
Name: myfirsteverpackagesfrompackageanditisunique
Version: 0.1
Summary: A simple package for calculating factorials
